LICENSE.txt
README.md
setup.cfg
setup.py
elastic_st/__init__.py
elastic_st/analysis.py
elastic_st/coefficient_analysis.py
elastic_st/data.py
elastic_st/elastic_st.py
elastic_st/features.py
elastic_st/spatial_statistics.py
elastic_st/weighted_elastic_net.c
elastic_st.egg-info/PKG-INFO
elastic_st.egg-info/SOURCES.txt
elastic_st.egg-info/dependency_links.txt
elastic_st.egg-info/requires.txt
elastic_st.egg-info/top_level.txt