Metadata-Version: 2.1
Name: elastic_st
Version: 0.1.1
Summary: A python data science library to build and analyze biological networks from spatial transcriptomics data. Allows inclusion of spatial information into the networks, going a step beyond graphs derived from scRNA-seq techniques.
Home-page: https://github.com/ThomasGust/Elastic-ST/
Author: Thomas Gust
Author-email: thomasgust@seattleacademy.org
Classifier: Programming Language :: Python :: 3
Classifier: Programming Language :: Cython
Classifier: Operating System :: OS Independent
Requires-Python: >=3.6
License-File: LICENSE.txt
Requires-Dist: numpy
Requires-Dist: scipy
Requires-Dist: scikit-learn
Requires-Dist: matplotlib
Requires-Dist: networkx
